retsly
