Metadata-Version: 1.1
Name: retsly
Version: 1.0.7
Summary: A Python wrapper for the Retsly API (https://rets.ly)
Home-page: https://github.com/retsly/retsly-python-sdk
Author: Retsly Software Inc.
Author-email: support@rets.ly
License: MIT
Keywords: retsly python sdk
Platform: UNKNOWN
Classifier: Development Status :: 5 - Production/Stable
Classifier: License :: OSI Approved :: MIT License
Classifier: Programming Language :: Python :: 2.7
